<ti:work xmlns:ti="http://chs.harvard.edu/xmlns/cts" groupUrn="urn:cts:greekLit:tlg2034" xml:lang="grc" urn="urn:cts:greekLit:tlg2034.tlg027">
  <ti:title xml:lang="lat">Historia philosophiae (fragmenta)</ti:title>
  <ti:edition urn="urn:cts:greekLit:tlg2034.tlg027.1st1K-grc1" workUrn="urn:cts:greekLit:tlg2034.tlg027">
    <ti:label xml:lang="lat">Historia philosophiae (fragmenta)</ti:label>
    <ti:description xml:lang="mul">Porphyrius, Historia philosophiae (fragmenta), Nauck, Teubner, 1860</ti:description>
  </ti:edition>
</ti:work>
