<ti:work xmlns:ti="http://chs.harvard.edu/xmlns/cts" groupUrn="urn:cts:greekLit:tlg4024" xml:lang="grc" urn="urn:cts:greekLit:tlg4024.tlg002">
  <ti:title xml:lang="lat">Epigrammata</ti:title>
  <ti:edition urn="urn:cts:greekLit:tlg4024.tlg002.opp-grc12" workUrn="urn:cts:greekLit:tlg4024.tlg002">
    <ti:label xml:lang="lat">Epigrammata</ti:label>
    <ti:description xml:lang="mul">Agathias Scholasticus, Epigrammata, Corpus Scriptorum Historiae Byzantinae, Vol 1,
    Niebuhr, Weber, 1828</ti:description>
  </ti:edition>
</ti:work>
