<ti:work xmlns:ti="http://chs.harvard.edu/xmlns/cts" groupUrn="urn:cts:greekLit:tlg2035" xml:lang="grc" urn="urn:cts:greekLit:tlg2035.tlg002">
  <ti:title xml:lang="lat">De Incarnatione Verbi</ti:title>
  
  <ti:edition urn="urn:cts:greekLit:tlg2035.tlg002.1st1K-grc1" workUrn="urn:cts:greekLit:tlg2035.tlg002" xml:lang="grc">
    <ti:label xml:lang="lat">De Incarnatione Verbi</ti:label>
    <ti:description xml:lang="eng">Athenasius of Alexandria. St. Athanasius On The Incarnation. Robertson, Archibald, editor. London: David Nutt, 1893.</ti:description>
  </ti:edition>
  
</ti:work>
