<ti:work xmlns:ti="http://chs.harvard.edu/xmlns/cts" groupUrn="urn:cts:greekLit:tlg0557" xml:lang="grc" urn="urn:cts:greekLit:tlg0557.tlg005">
    <ti:title xml:lang="lat">Gnomologium Epicteteum (e Stobaei libris 3‑4)</ti:title>
    
  <ti:edition urn="urn:cts:greekLit:tlg0557.tlg005.1st1K-grc1" workUrn="urn:cts:greekLit:tlg0557.tlg005">
      <ti:label xml:lang="lat">Gnomologium Epicteteum (e Stobaei libris 3‑4)</ti:label>
      <ti:description xml:lang="mul">Epictetus. Epicteti Dissertationes ab Arriano Digestae. Schenkl, Heinrich, editor. Leipzig:Teubner, 1916.</ti:description>
  </ti:edition>
</ti:work>
